reflex_clerk/__init__.py
reflex_clerk/clerk_client/__init__.py
reflex_clerk/clerk_client/clerk_client.py
reflex_clerk/clerk_client/clerk_request_models.py
reflex_clerk/clerk_client/clerk_response_models.py
reflex_clerk/lib/__init__.py
reflex_clerk/lib/appearance.py
reflex_clerk/lib/clerk_provider.py
reflex_clerk/lib/control.py
reflex_clerk/lib/reflex_clerk.py
reflex_clerk/lib/sign_in.py
reflex_clerk/lib/sign_out.py
reflex_clerk/lib/sign_up.py
reflex_clerk/lib/user.py
reflex_clerk-1.0.3.dist-info/METADATA
reflex_clerk-1.0.3.dist-info/WHEEL
reflex_clerk-1.0.3.dist-info/top_level.txt
reflex_clerk-1.0.3.dist-info/RECORD
