Metadata-Version: 2.1
Name: reflex-clerk
Version: 1.0.3
Summary: Reflex custom component library for Clerk, a user management platform
Author-email: Elliot Kroo <elliot@kroo.net>
License: Apache-2.0
Project-URL: homepage, https://kroo.github.io/reflex-clerk/
Project-URL: source, https://github.com/kroo/reflex-clerk
Keywords: reflex,reflex-custom-components
Classifier: Development Status :: 4 - Beta
Requires-Python: >=3.8
Requires-Dist: reflex >=0.5.0
Provides-Extra: dev
Requires-Dist: build ; extra == 'dev'
Requires-Dist: twine ; extra == 'dev'
